{
  "run_id": "cifar10_wan_campaign__smoke__20260604T234837",
  "cluster_name": "cifar10_wan_campaign__smoke__20260604T234837",
  "self_node_id": "decentr-15",
  "device": "cpu",
  "dataset": "CIFAR10",
  "model": "resnet18",
  "mode": "async",
  "algorithm": "local_sgd",
  "history_kind": "epochs",
  "started_at": "2026-06-04T21:49:17.900595+00:00",
  "finished_at": "2026-06-04T22:03:32.809822+00:00",
  "run_duration_s": 844.9044201580109,
  "cluster_node_count": 20,
  "epoch_count": 2,
  "local_train_sample_count": 1024,
  "total_samples_processed": 3584,
  "effective_samples_per_s": 4.241899929141965,
  "best_val_accuracy": 0.1732,
  "best_test_accuracy": 0.168,
  "best_val_macro_f1": 0.11595245598485944,
  "best_test_macro_f1": 0.11376155535138469,
  "metrics_file": "async_epoch_metrics.csv",
  "scheduler_history_file": "artifacts/logs/cifar10_wan_campaign__smoke__20260604T234837/decentr-15/scheduler_history.csv",
  "transport_address": "0.0.0.0:50051",
  "advertise_address": "192.168.199.42:50051",
  "neighbor_ids": [
    "decentr-01",
    "decentr-02",
    "decentr-03",
    "decentr-04",
    "decentr-05",
    "decentr-06",
    "decentr-07",
    "decentr-08",
    "decentr-09",
    "decentr-10",
    "decentr-11",
    "decentr-12",
    "decentr-13",
    "decentr-14",
    "decentr-16",
    "decentr-17",
    "decentr-18",
    "decentr-19",
    "decentr-20"
  ],
  "mixed_peer_updates_total": 77,
  "dropped_peer_updates_total": 0,
  "nonfinite_peer_updates_total": 0,
  "max_observed_staleness": 32,
  "max_observed_normalized_staleness": 32.0,
  "stale_mixed_peer_updates_total": 25,
  "hard_dropped_stale_peer_updates_total": 0,
  "failed_pushes_total": 0,
  "push_count_total": 95,
  "push_elapsed_s_total": 280.7607919428556,
  "push_failed_targets_total": [],
  "push_failure_reasons_total": [],
  "max_local_step": 112,
  "epochs": [
    {
      "epoch": 1,
      "local_train_loss": 2.3321265459060667,
      "local_train_accuracy": 0.113671875,
      "local_train_macro_f1": 0.11037614681861665,
      "samples_processed": 2560,
      "duration_s": 434.0071089170233,
      "mixed_peer_updates": 36,
      "mixed_senders": [
        "decentr-01",
        "decentr-02",
        "decentr-03",
        "decentr-04",
        "decentr-05",
        "decentr-06",
        "decentr-07",
        "decentr-08",
        "decentr-09",
        "decentr-10",
        "decentr-11",
        "decentr-12",
        "decentr-13",
        "decentr-14",
        "decentr-16",
        "decentr-17",
        "decentr-18",
        "decentr-19",
        "decentr-20"
      ],
      "dropped_peer_updates": 0,
      "dropped_peer_senders": [],
      "drop_reasons": [],
      "nonfinite_peer_updates": 0,
      "max_staleness": 16,
      "max_normalized_staleness": 16.0,
      "stale_mixed_peer_updates": 16,
      "hard_dropped_stale_peer_updates": 0,
      "pushes_sent": 38,
      "failed_pushes_total": 0,
      "push_elapsed_s": 117.92090920102783,
      "push_failed_targets": [],
      "push_failure_reasons": [],
      "window_count": 2,
      "val_loss": 2.258160677719116,
      "val_accuracy": 0.156,
      "val_macro_f1": 0.10741974792385603,
      "test_loss": 2.2574357856750487,
      "test_accuracy": 0.1501,
      "test_macro_f1": 0.10186327404012963,
      "state_digest": "fc85656ee62397d5cfce1bb51cfb95d5d798effaa895d5e98672924f8dfe5e14",
      "last_step": 80,
      "windows": [
        {
          "window_id": 0,
          "epoch_window_index": 0,
          "epoch_window_count": 2,
          "assigned_shard_count": 3,
          "samples_processed": 1536,
          "duration_s": 138.02465532999486
        },
        {
          "window_id": 1,
          "epoch_window_index": 1,
          "epoch_window_count": 2,
          "assigned_shard_count": 2,
          "samples_processed": 1024,
          "duration_s": 107.35775729300804
        }
      ],
      "samples_per_s": 5.8985208937889535
    },
    {
      "epoch": 2,
      "local_train_loss": 2.2548048943281174,
      "local_train_accuracy": 0.1689453125,
      "local_train_macro_f1": 0.15332872036847528,
      "samples_processed": 1024,
      "duration_s": 410.20353359001456,
      "mixed_peer_updates": 41,
      "mixed_senders": [
        "decentr-01",
        "decentr-02",
        "decentr-03",
        "decentr-04",
        "decentr-05",
        "decentr-06",
        "decentr-07",
        "decentr-08",
        "decentr-09",
        "decentr-10",
        "decentr-11",
        "decentr-12",
        "decentr-13",
        "decentr-14",
        "decentr-16",
        "decentr-17",
        "decentr-18",
        "decentr-19",
        "decentr-20"
      ],
      "dropped_peer_updates": 0,
      "dropped_peer_senders": [],
      "drop_reasons": [],
      "nonfinite_peer_updates": 0,
      "max_staleness": 32,
      "max_normalized_staleness": 32.0,
      "stale_mixed_peer_updates": 9,
      "hard_dropped_stale_peer_updates": 0,
      "pushes_sent": 57,
      "failed_pushes_total": 0,
      "push_elapsed_s": 162.83988274182775,
      "push_failed_targets": [],
      "push_failure_reasons": [],
      "window_count": 2,
      "val_loss": 2.225908517456055,
      "val_accuracy": 0.1732,
      "val_macro_f1": 0.11595245598485944,
      "test_loss": 2.224818048095703,
      "test_accuracy": 0.168,
      "test_macro_f1": 0.11376155535138469,
      "state_digest": "c07d17d7005b86f4609e5553ded14f09c6ae27e1520402a1773cc364b94ad35b",
      "last_step": 112,
      "windows": [
        {
          "window_id": 2,
          "epoch_window_index": 0,
          "epoch_window_count": 2,
          "assigned_shard_count": 1,
          "samples_processed": 512,
          "duration_s": 80.9118073550053
        },
        {
          "window_id": 3,
          "epoch_window_index": 1,
          "epoch_window_count": 2,
          "assigned_shard_count": 1,
          "samples_processed": 512,
          "duration_s": 137.73656333301915
        }
      ],
      "samples_per_s": 2.4963217431068148
    }
  ],
  "received_payload_count": 96,
  "final_test_metrics": {
    "loss": 2.224818048095703,
    "accuracy": 0.168,
    "macro_f1": 0.11376155535138469
  },
  "final_state_digest": "c07d17d7005b86f4609e5553ded14f09c6ae27e1520402a1773cc364b94ad35b",
  "data_plane_stats": {
    "bytes_transferred": 0,
    "shards_pulled": 0,
    "prefetch_hits": 2,
    "prefetch_misses": 2,
    "prefetch_failures": 0,
    "prefetch_wait_s": 0.010781918012071401,
    "window_wait_s": 0.11577651597326621,
    "evicted_shards": 0,
    "evicted_bytes": 0,
    "train_shard_requests": 10,
    "cache_hits": 10,
    "cache_misses": 0,
    "transfer_retry_count": 0,
    "transfer_retry_backoff_s": 0.0,
    "cache_hit_rate": 1.0
  },
  "control_plane_role": "follower",
  "completion_reported": true,
  "completion_cluster_complete": null,
  "completion_seen_count": 1,
  "missing_completion_nodes": []
}